fastapi_third_party_auth/__init__.py
fastapi_third_party_auth/auth.py
fastapi_third_party_auth/discovery.py
fastapi_third_party_auth/grant_types.py
fastapi_third_party_auth/idtoken_types.py
fastapi_third_party_auth-0.1.2.dist-info/LICENSE
fastapi_third_party_auth-0.1.2.dist-info/WHEEL
fastapi_third_party_auth-0.1.2.dist-info/METADATA
fastapi_third_party_auth-0.1.2.dist-info/RECORD
