Metadata-Version: 2.1
Name: fastapi-third-party-auth
Version: 0.1.2
Summary: Simple library for using a third party authentication service like Keycloak or Auth0 with FastAPI
Home-page: https://github.com/aiwizo/fastapi-third-party-auth
License: MIT
Author: HarryMWinters
Author-email: harrymcwinters@gmail.com
Requires-Python: >=3.8,<4.0
Classifier: License :: OSI Approved :: MIT License
Classifier: Programming Language :: Python :: 3
Classifier: Programming Language :: Python :: 3.8
Classifier: Programming Language :: Python :: 3.9
Classifier: Programming Language :: Python :: 3.10
Provides-Extra: docs
Requires-Dist: cachetools (>=4.1.1)
Requires-Dist: fastapi (>=0.61.0)
Requires-Dist: pydantic (>=1.6.1)
Requires-Dist: python-jose[cryptography] (>=3.2.0)
Requires-Dist: requests (>=2.24.0)
Project-URL: Documentation, https://fastapi-third-party-auth.readthedocs.io/en/latest/
Project-URL: Repository, https://github.com/aiwizo/fastapi-third-party-auth
